{"version":1.3,"people":[{"person_id":[-1],"pose_keypoints_2d":[35.8073,341.965,0.929381,0,0,0,0,0,0,0,0,0,0,0,0,0,0,0,0,0,0,0,0,0,0,0,0,0,0,0,0,0,0,0,0,0,0,0,0,0,0,0,0,0,0,7.77015,318.423,0.966577,50.4768,324.259,0.80848,7.83915,318.581,0.0502138,0,0,0,0,0,0,0,0,0,0,0,0,0,0,0,0,0,0,0,0,0],"face_keypoints_2d":[],"hand_left_keypoints_2d":[],"hand_right_keypoints_2d":[],"pose_keypoints_3d":[],"face_keypoints_3d":[],"hand_left_keypoints_3d":[],"hand_right_keypoints_3d":[]},{"person_id":[-1],"pose_keypoints_2d":[0,0,0,0,0,0,0,0,0,0,0,0,0,0,0,35.9563,471.459,0.734421,44.6808,609.796,0.580385,47.5764,718.795,0.717153,0,0,0,0,0,0,0,0,0,0,0,0,0,0,0,0,0,0,0,0,0,0,0,0,0,0,0,0,0,0,0,0,0,0,0,0,0,0,0,0,0,0,0,0,0,0,0,0,0,0,0],"face_keypoints_2d":[],"hand_left_keypoints_2d":[],"hand_right_keypoints_2d":[],"pose_keypoints_3d":[],"face_keypoints_3d":[],"hand_left_keypoints_3d":[],"hand_right_keypoints_3d":[]}]}